[
    {
        "date": "2025-09-30",
        "symbol": "F",
        "reportedCurrency": "USD",
        "cik": "0000037996",
        "filingDate": "2025-10-24",
        "acceptedDate": "2025-10-23 19:12:04",
        "fiscalYear": "2025",
        "period": "Q3",
        "revenue": 50534000000,
        "costOfRevenue": 46236000000,
        "grossProfit": 4298000000,
        "researchAndDevelopmentExpenses": 0,
        "generalAndAdministrativeExpenses": 0,
        "sellingAndMarketingExpenses": 0,
        "sellingGeneralAndAdministrativeExpenses": 2740000000,
        "otherExpenses": 0,
        "operatingExpenses": 2740000000,
        "costAndExpenses": 48976000000,
        "netInterestIncome": 46000000,
        "interestIncome": 367000000,
        "interestExpense": 321000000,
        "depreciationAndAmortization": 1522000000,
        "ebitda": 3661000000,
        "ebit": 2139000000,
        "nonOperatingIncomeExcludingInterest": -581000000,
        "operatingIncome": 1558000000,
        "totalOtherIncomeExpensesNet": 260000000,
        "incomeBeforeTax": 1818000000,
        "incomeTaxExpense": -630000000,
        "netIncomeFromContinuingOperations": 2448000000,
        "netIncomeFromDiscontinuedOperations": 0,
        "otherAdjustmentsToNetIncome": 0,
        "netIncome": 2447000000,
        "netIncomeDeductions": 0,
        "bottomLineNetIncome": 2447000000,
        "eps": 0.61,
        "epsDiluted": 0.6,
        "weightedAverageShsOut": 3983000000,
        "weightedAverageShsOutDil": 4048000000
    },
    {
        "date": "2024-09-30",
        "symbol": "F",
        "reportedCurrency": "USD",
        "cik": "0000037996",
        "filingDate": "2024-10-29",
        "acceptedDate": "2024-10-28 19:24:49",
        "fiscalYear": "2024",
        "period": "Q3",
        "revenue": 46196000000,
        "costOfRevenue": 42860000000,
        "grossProfit": 3336000000,
        "researchAndDevelopmentExpenses": 0,
        "generalAndAdministrativeExpenses": 0,
        "sellingAndMarketingExpenses": 0,
        "sellingGeneralAndAdministrativeExpenses": 2456000000,
        "otherExpenses": 0,
        "operatingExpenses": 2456000000,
        "costAndExpenses": 45316000000,
        "netInterestIncome": 94000000,
        "interestIncome": 367000000,
        "interestExpense": 273000000,
        "depreciationAndAmortization": 1394000000,
        "ebitda": 2536000000,
        "ebit": 1142000000,
        "nonOperatingIncomeExcludingInterest": -262000000,
        "operatingIncome": 880000000,
        "totalOtherIncomeExpensesNet": -11000000,
        "incomeBeforeTax": 869000000,
        "incomeTaxExpense": -27000000,
        "netIncomeFromContinuingOperations": 896000000,
        "netIncomeFromDiscontinuedOperations": 0,
        "otherAdjustmentsToNetIncome": 0,
        "netIncome": 892000000,
        "netIncomeDeductions": 0,
        "bottomLineNetIncome": 892000000,
        "eps": 0.22,
        "epsDiluted": 0.22,
        "weightedAverageShsOut": 3976000000,
        "weightedAverageShsOutDil": 4018000000
    },
    {
        "date": "2023-09-30",
        "symbol": "F",
        "reportedCurrency": "USD",
        "cik": "0000037996",
        "filingDate": "2023-10-27",
        "acceptedDate": "2023-10-26 19:41:47",
        "fiscalYear": "2023",
        "period": "Q3",
        "revenue": 43801000000,
        "costOfRevenue": 40001000000,
        "grossProfit": 3800000000,
        "researchAndDevelopmentExpenses": 0,
        "generalAndAdministrativeExpenses": 0,
        "sellingAndMarketingExpenses": 0,
        "sellingGeneralAndAdministrativeExpenses": 2671000000,
        "otherExpenses": 0,
        "operatingExpenses": 2671000000,
        "costAndExpenses": 42672000000,
        "netInterestIncome": 84000000,
        "interestIncome": 414000000,
        "interestExpense": 330000000,
        "depreciationAndAmortization": 1604000000,
        "ebitda": 3321000000,
        "ebit": 1717000000,
        "nonOperatingIncomeExcludingInterest": -588000000,
        "operatingIncome": 1129000000,
        "totalOtherIncomeExpensesNet": 258000000,
        "incomeBeforeTax": 1387000000,
        "incomeTaxExpense": 214000000,
        "netIncomeFromContinuingOperations": 1173000000,
        "netIncomeFromDiscontinuedOperations": 0,
        "otherAdjustmentsToNetIncome": 0,
        "netIncome": 1199000000,
        "netIncomeDeductions": 0,
        "bottomLineNetIncome": 1199000000,
        "eps": 0.3,
        "epsDiluted": 0.3,
        "weightedAverageShsOut": 4004000000,
        "weightedAverageShsOutDil": 4050000000
    },
    {
        "date": "2022-09-30",
        "symbol": "F",
        "reportedCurrency": "USD",
        "cik": "0000037996",
        "filingDate": "2022-10-27",
        "acceptedDate": "2022-10-26 19:18:39",
        "fiscalYear": "2022",
        "period": "Q3",
        "revenue": 39392000000,
        "costOfRevenue": 36041000000,
        "grossProfit": 3351000000,
        "researchAndDevelopmentExpenses": 0,
        "generalAndAdministrativeExpenses": 0,
        "sellingAndMarketingExpenses": 0,
        "sellingGeneralAndAdministrativeExpenses": 2847000000,
        "otherExpenses": 0,
        "operatingExpenses": 2847000000,
        "costAndExpenses": 38888000000,
        "netInterestIncome": -139000000,
        "interestIncome": 182000000,
        "interestExpense": 321000000,
        "depreciationAndAmortization": 1627000000,
        "ebitda": 823000000,
        "ebit": -804000000,
        "nonOperatingIncomeExcludingInterest": 1308000000,
        "operatingIncome": 504000000,
        "totalOtherIncomeExpensesNet": -1629000000,
        "incomeBeforeTax": -1125000000,
        "incomeTaxExpense": -195000000,
        "netIncomeFromContinuingOperations": -930000000,
        "netIncomeFromDiscontinuedOperations": 0,
        "otherAdjustmentsToNetIncome": 0,
        "netIncome": -827000000,
        "netIncomeDeductions": 0,
        "bottomLineNetIncome": -827000000,
        "eps": -0.21,
        "epsDiluted": -0.21,
        "weightedAverageShsOut": 4021000000,
        "weightedAverageShsOutDil": 4021000000
    },
    {
        "date": "2021-09-30",
        "symbol": "F",
        "reportedCurrency": "USD",
        "cik": "0000037996",
        "filingDate": "2021-10-28",
        "acceptedDate": "2021-10-27 18:22:16",
        "fiscalYear": "2021",
        "period": "Q3",
        "revenue": 35683000000,
        "costOfRevenue": 31394000000,
        "grossProfit": 4289000000,
        "researchAndDevelopmentExpenses": 0,
        "generalAndAdministrativeExpenses": 0,
        "sellingAndMarketingExpenses": 0,
        "sellingGeneralAndAdministrativeExpenses": 2947000000,
        "otherExpenses": 0,
        "operatingExpenses": 2947000000,
        "costAndExpenses": 34341000000,
        "netInterestIncome": -376000000,
        "interestIncome": 63000000,
        "interestExpense": 439000000,
        "depreciationAndAmortization": 1520000000,
        "ebitda": 3844000000,
        "ebit": 2324000000,
        "nonOperatingIncomeExcludingInterest": -982000000,
        "operatingIncome": 1342000000,
        "totalOtherIncomeExpensesNet": 543000000,
        "incomeBeforeTax": 1885000000,
        "incomeTaxExpense": 63000000,
        "netIncomeFromContinuingOperations": 1822000000,
        "netIncomeFromDiscontinuedOperations": 0,
        "otherAdjustmentsToNetIncome": 0,
        "netIncome": 1832000000,
        "netIncomeDeductions": 0,
        "bottomLineNetIncome": 1832000000,
        "eps": 0.46,
        "epsDiluted": 0.45,
        "weightedAverageShsOut": 3995000000,
        "weightedAverageShsOutDil": 4036000000
    }
]