[
    {
        "date": "2025-06-30",
        "symbol": "MGM",
        "reportedCurrency": "USD",
        "cik": "0000789570",
        "filingDate": "2025-07-30",
        "acceptedDate": "2025-07-30 16:19:02",
        "fiscalYear": "2025",
        "period": "Q2",
        "revenue": 4404870000,
        "costOfRevenue": 2445429000,
        "grossProfit": 1959441000,
        "researchAndDevelopmentExpenses": 0,
        "generalAndAdministrativeExpenses": 1213691000,
        "sellingAndMarketingExpenses": 0,
        "sellingGeneralAndAdministrativeExpenses": 1213691000,
        "otherExpenses": 341185000,
        "operatingExpenses": 1554876000,
        "costAndExpenses": 4000305000,
        "netInterestIncome": -105584000,
        "interestIncome": 0,
        "interestExpense": 105584000,
        "depreciationAndAmortization": 241975000,
        "ebitda": 481315000,
        "ebit": 239340000,
        "nonOperatingIncomeExcludingInterest": 165225000,
        "operatingIncome": 404565000,
        "totalOtherIncomeExpensesNet": -270809000,
        "incomeBeforeTax": 133756000,
        "incomeTaxExpense": 15662000,
        "netIncomeFromContinuingOperations": 118094000,
        "netIncomeFromDiscontinuedOperations": 0,
        "otherAdjustmentsToNetIncome": 0,
        "netIncome": 48951000,
        "netIncomeDeductions": 0,
        "bottomLineNetIncome": 48982000,
        "eps": 0.18,
        "epsDiluted": 0.18,
        "weightedAverageShsOut": 273329000,
        "weightedAverageShsOutDil": 275615000
    },
    {
        "date": "2024-06-30",
        "symbol": "MGM",
        "reportedCurrency": "USD",
        "cik": "0000789570",
        "filingDate": "2024-07-31",
        "acceptedDate": "2024-07-31 16:19:04",
        "fiscalYear": "2024",
        "period": "Q2",
        "revenue": 4327375000,
        "costOfRevenue": 2323181000,
        "grossProfit": 2004194000,
        "researchAndDevelopmentExpenses": 0,
        "generalAndAdministrativeExpenses": 759788000,
        "sellingAndMarketingExpenses": 576113000,
        "sellingGeneralAndAdministrativeExpenses": 1335901000,
        "otherExpenses": 242637000,
        "operatingExpenses": 1578538000,
        "costAndExpenses": 3901719000,
        "netInterestIncome": -112739000,
        "interestIncome": 0,
        "interestExpense": 112739000,
        "depreciationAndAmortization": 191976000,
        "ebitda": 668293000,
        "ebit": 476317000,
        "nonOperatingIncomeExcludingInterest": -50661000,
        "operatingIncome": 425656000,
        "totalOtherIncomeExpensesNet": -154408000,
        "incomeBeforeTax": 271248000,
        "incomeTaxExpense": -11554000,
        "netIncomeFromContinuingOperations": 282802000,
        "netIncomeFromDiscontinuedOperations": 0,
        "otherAdjustmentsToNetIncome": 0,
        "netIncome": 187072000,
        "netIncomeDeductions": -1.5235855244100094e-08,
        "bottomLineNetIncome": 187170000,
        "eps": 0.6,
        "epsDiluted": 0.6,
        "weightedAverageShsOut": 311179000,
        "weightedAverageShsOutDil": 314420000
    },
    {
        "date": "2023-06-30",
        "symbol": "MGM",
        "reportedCurrency": "USD",
        "cik": "0000789570",
        "filingDate": "2023-08-02",
        "acceptedDate": "2023-08-02 16:19:36",
        "fiscalYear": "2023",
        "period": "Q2",
        "revenue": 3942207000,
        "costOfRevenue": 2083896000,
        "grossProfit": 1858311000,
        "researchAndDevelopmentExpenses": 0,
        "generalAndAdministrativeExpenses": 1144390000,
        "sellingAndMarketingExpenses": 0,
        "sellingGeneralAndAdministrativeExpenses": 1144390000,
        "otherExpenses": 342543000,
        "operatingExpenses": 1486933000,
        "costAndExpenses": 3570829000,
        "netInterestIncome": -111945000,
        "interestIncome": 0,
        "interestExpense": 111945000,
        "depreciationAndAmortization": 203503000,
        "ebitda": 598133000,
        "ebit": 394630000,
        "nonOperatingIncomeExcludingInterest": -23252000,
        "operatingIncome": 371378000,
        "totalOtherIncomeExpensesNet": -88693000,
        "incomeBeforeTax": 282685000,
        "incomeTaxExpense": 39141000,
        "netIncomeFromContinuingOperations": 243544000,
        "netIncomeFromDiscontinuedOperations": 0,
        "otherAdjustmentsToNetIncome": 0,
        "netIncome": 200796000,
        "netIncomeDeductions": 0,
        "bottomLineNetIncome": 200910000,
        "eps": 0.56,
        "epsDiluted": 0.55,
        "weightedAverageShsOut": 361050000,
        "weightedAverageShsOutDil": 365339000
    },
    {
        "date": "2022-06-30",
        "symbol": "MGM",
        "reportedCurrency": "USD",
        "cik": "0000789570",
        "filingDate": "2022-08-03",
        "acceptedDate": "2022-08-03 16:45:51",
        "fiscalYear": "2022",
        "period": "Q2",
        "revenue": 3254964000,
        "costOfRevenue": 1599900000,
        "grossProfit": 1655064000,
        "researchAndDevelopmentExpenses": 0,
        "generalAndAdministrativeExpenses": 1148375000,
        "sellingAndMarketingExpenses": 542000,
        "sellingGeneralAndAdministrativeExpenses": 1148917000,
        "otherExpenses": -1875304000,
        "operatingExpenses": -726387000,
        "costAndExpenses": 873513000,
        "netInterestIncome": -136559000,
        "interestIncome": 0,
        "interestExpense": 136559000,
        "depreciationAndAmortization": 366255000,
        "ebitda": 506147000,
        "ebit": 139892000,
        "nonOperatingIncomeExcludingInterest": 2241559000,
        "operatingIncome": 2381451000,
        "totalOtherIncomeExpensesNet": -185987000,
        "incomeBeforeTax": 2195464000,
        "incomeTaxExpense": 572839000,
        "netIncomeFromContinuingOperations": 1622625000,
        "netIncomeFromDiscontinuedOperations": 0,
        "otherAdjustmentsToNetIncome": 0,
        "netIncome": 1783937000,
        "netIncomeDeductions": 1,
        "bottomLineNetIncome": 1771525000,
        "eps": 4.24,
        "epsDiluted": 4.2,
        "weightedAverageShsOut": 417393000,
        "weightedAverageShsOutDil": 421303000
    },
    {
        "date": "2021-06-30",
        "symbol": "MGM",
        "reportedCurrency": "USD",
        "cik": "0000789570",
        "filingDate": "2021-08-06",
        "acceptedDate": "2021-08-06 09:01:31",
        "fiscalYear": "2021",
        "period": "Q2",
        "revenue": 2192829000,
        "costOfRevenue": 1070519000,
        "grossProfit": 1122310000,
        "researchAndDevelopmentExpenses": 0,
        "generalAndAdministrativeExpenses": 687079000,
        "sellingAndMarketingExpenses": 90000,
        "sellingGeneralAndAdministrativeExpenses": 687169000,
        "otherExpenses": 171381000,
        "operatingExpenses": 858550000,
        "costAndExpenses": 1929069000,
        "netInterestIncome": -202772000,
        "interestIncome": 0,
        "interestExpense": 202772000,
        "depreciationAndAmortization": 283625000,
        "ebitda": 435141000,
        "ebit": 151516000,
        "nonOperatingIncomeExcludingInterest": 112244000,
        "operatingIncome": 263760000,
        "totalOtherIncomeExpensesNet": -138630000,
        "incomeBeforeTax": 125130000,
        "incomeTaxExpense": 34826000,
        "netIncomeFromContinuingOperations": 90304000,
        "netIncomeFromDiscontinuedOperations": 0,
        "otherAdjustmentsToNetIncome": 0,
        "netIncome": 104753000,
        "netIncomeDeductions": 1,
        "bottomLineNetIncome": 67742000,
        "eps": 0.21,
        "epsDiluted": 0.21,
        "weightedAverageShsOut": 489459000,
        "weightedAverageShsOutDil": 495302000
    }
]