[
    {
        "date": "2025-09-30",
        "symbol": "ROKU",
        "reportedCurrency": "USD",
        "cik": "0001428439",
        "filingDate": "2025-10-31",
        "acceptedDate": "2025-10-31 16:06:54",
        "fiscalYear": "2025",
        "period": "Q3",
        "revenue": 1210638000,
        "costOfRevenue": 685739000,
        "grossProfit": 524899000,
        "researchAndDevelopmentExpenses": 182235000,
        "generalAndAdministrativeExpenses": 91121000,
        "sellingAndMarketingExpenses": 242077000,
        "sellingGeneralAndAdministrativeExpenses": 333198000,
        "otherExpenses": 0,
        "operatingExpenses": 515433000,
        "costAndExpenses": 1201172000,
        "netInterestIncome": -455000,
        "interestIncome": 0,
        "interestExpense": 455000,
        "depreciationAndAmortization": 19441000,
        "ebitda": 57926000,
        "ebit": 38485000,
        "nonOperatingIncomeExcludingInterest": -29019000,
        "operatingIncome": 9466000,
        "totalOtherIncomeExpensesNet": 28564000,
        "incomeBeforeTax": 38030000,
        "incomeTaxExpense": 13218000,
        "netIncomeFromContinuingOperations": 24812000,
        "netIncomeFromDiscontinuedOperations": 0,
        "otherAdjustmentsToNetIncome": 0,
        "netIncome": 24812000,
        "netIncomeDeductions": 0,
        "bottomLineNetIncome": 24812000,
        "eps": 0.17,
        "epsDiluted": 0.16,
        "weightedAverageShsOut": 146855000,
        "weightedAverageShsOutDil": 150449000
    },
    {
        "date": "2024-09-30",
        "symbol": "ROKU",
        "reportedCurrency": "USD",
        "cik": "0001428439",
        "filingDate": "2024-10-31",
        "acceptedDate": "2024-10-31 16:01:59",
        "fiscalYear": "2024",
        "period": "Q3",
        "revenue": 1062203000,
        "costOfRevenue": 582128000,
        "grossProfit": 480075000,
        "researchAndDevelopmentExpenses": 178798000,
        "generalAndAdministrativeExpenses": 97094000,
        "sellingAndMarketingExpenses": 220059000,
        "sellingGeneralAndAdministrativeExpenses": 317153000,
        "otherExpenses": 0,
        "operatingExpenses": 497317000,
        "costAndExpenses": 1079445000,
        "netInterestIncome": 0,
        "interestIncome": 0,
        "interestExpense": 0,
        "depreciationAndAmortization": 78077000,
        "ebitda": 73194000,
        "ebit": -4882999,
        "nonOperatingIncomeExcludingInterest": -12359000,
        "operatingIncome": -17242000,
        "totalOtherIncomeExpensesNet": 12359000,
        "incomeBeforeTax": -4883000,
        "incomeTaxExpense": 4147000,
        "netIncomeFromContinuingOperations": -9030000,
        "netIncomeFromDiscontinuedOperations": 0,
        "otherAdjustmentsToNetIncome": 0,
        "netIncome": -9030000,
        "netIncomeDeductions": 0,
        "bottomLineNetIncome": -9030000,
        "eps": -0.0623,
        "epsDiluted": -0.0623,
        "weightedAverageShsOut": 144862000,
        "weightedAverageShsOutDil": 144862000
    },
    {
        "date": "2023-09-30",
        "symbol": "ROKU",
        "reportedCurrency": "USD",
        "cik": "0001428439",
        "filingDate": "2023-11-02",
        "acceptedDate": "2023-11-02 16:22:49",
        "fiscalYear": "2023",
        "period": "Q3",
        "revenue": 912018000,
        "costOfRevenue": 543195000,
        "grossProfit": 368823000,
        "researchAndDevelopmentExpenses": 282201000,
        "generalAndAdministrativeExpenses": 128717000,
        "sellingAndMarketingExpenses": 307694000,
        "sellingGeneralAndAdministrativeExpenses": 436411000,
        "otherExpenses": 0,
        "operatingExpenses": 718612000,
        "costAndExpenses": 1261807000,
        "netInterestIncome": -10000,
        "interestIncome": 0,
        "interestExpense": 10000,
        "depreciationAndAmortization": 85911000,
        "ebitda": -220967000,
        "ebit": -306878000,
        "nonOperatingIncomeExcludingInterest": -42911000,
        "operatingIncome": -349789000,
        "totalOtherIncomeExpensesNet": 22902000,
        "incomeBeforeTax": -326887000,
        "incomeTaxExpense": 3184000,
        "netIncomeFromContinuingOperations": -330071000,
        "netIncomeFromDiscontinuedOperations": 0,
        "otherAdjustmentsToNetIncome": 0,
        "netIncome": -330071000,
        "netIncomeDeductions": 0,
        "bottomLineNetIncome": -330071000,
        "eps": -2.33,
        "epsDiluted": -2.33,
        "weightedAverageShsOut": 141877000,
        "weightedAverageShsOutDil": 141877000
    },
    {
        "date": "2022-09-30",
        "symbol": "ROKU",
        "reportedCurrency": "USD",
        "cik": "0001428439",
        "filingDate": "2022-11-03",
        "acceptedDate": "2022-11-03 16:07:42",
        "fiscalYear": "2022",
        "period": "Q3",
        "revenue": 761373000,
        "costOfRevenue": 404586000,
        "grossProfit": 356787000,
        "researchAndDevelopmentExpenses": 207608000,
        "generalAndAdministrativeExpenses": 86804000,
        "sellingAndMarketingExpenses": 209364000,
        "sellingGeneralAndAdministrativeExpenses": 296168000,
        "otherExpenses": 0,
        "operatingExpenses": 503776000,
        "costAndExpenses": 908362000,
        "netInterestIncome": -1157000,
        "interestIncome": 0,
        "interestExpense": 1157000,
        "depreciationAndAmortization": 28632000,
        "ebitda": -90443000,
        "ebit": -119075000,
        "nonOperatingIncomeExcludingInterest": -27914000,
        "operatingIncome": -146989000,
        "totalOtherIncomeExpensesNet": 26757000,
        "incomeBeforeTax": -120232000,
        "incomeTaxExpense": 1951000,
        "netIncomeFromContinuingOperations": -122183000,
        "netIncomeFromDiscontinuedOperations": 0,
        "otherAdjustmentsToNetIncome": 0,
        "netIncome": -122183000,
        "netIncomeDeductions": 0,
        "bottomLineNetIncome": -122183000,
        "eps": -0.88,
        "epsDiluted": -0.88,
        "weightedAverageShsOut": 138571000,
        "weightedAverageShsOutDil": 138571000
    },
    {
        "date": "2021-09-30",
        "symbol": "ROKU",
        "reportedCurrency": "USD",
        "cik": "0001428439",
        "filingDate": "2021-11-04",
        "acceptedDate": "2021-11-04 16:51:39",
        "fiscalYear": "2021",
        "period": "Q3",
        "revenue": 679953000,
        "costOfRevenue": 316034000,
        "grossProfit": 363919000,
        "researchAndDevelopmentExpenses": 120307000,
        "generalAndAdministrativeExpenses": 65066000,
        "sellingAndMarketingExpenses": 109700000,
        "sellingGeneralAndAdministrativeExpenses": 174766000,
        "otherExpenses": 0,
        "operatingExpenses": 295073000,
        "costAndExpenses": 611107000,
        "netInterestIncome": -743000,
        "interestIncome": 0,
        "interestExpense": 743000,
        "depreciationAndAmortization": 18513000,
        "ebitda": 87859000,
        "ebit": 69346000,
        "nonOperatingIncomeExcludingInterest": -500000,
        "operatingIncome": 68846000,
        "totalOtherIncomeExpensesNet": -243000,
        "incomeBeforeTax": 68603000,
        "incomeTaxExpense": -332000,
        "netIncomeFromContinuingOperations": 68935000,
        "netIncomeFromDiscontinuedOperations": 0,
        "otherAdjustmentsToNetIncome": 0,
        "netIncome": 68935000,
        "netIncomeDeductions": 0,
        "bottomLineNetIncome": 68935000,
        "eps": 0.52,
        "epsDiluted": 0.48,
        "weightedAverageShsOut": 133685000,
        "weightedAverageShsOutDil": 142286000
    }
]