[
    {
        "date": "2024-12-31",
        "symbol": "RIVN",
        "reportedCurrency": "USD",
        "cik": "0001874178",
        "filingDate": "2025-02-24",
        "acceptedDate": "2025-02-24 17:08:34",
        "fiscalYear": "2024",
        "period": "Q4",
        "revenue": 1734000000,
        "costOfRevenue": 1564000000,
        "grossProfit": 170000000,
        "researchAndDevelopmentExpenses": 374000000,
        "generalAndAdministrativeExpenses": 0,
        "sellingAndMarketingExpenses": 0,
        "sellingGeneralAndAdministrativeExpenses": 457000000,
        "otherExpenses": 0,
        "operatingExpenses": 831000000,
        "costAndExpenses": 2395000000,
        "netInterestIncome": 2000000,
        "interestIncome": 83000000,
        "interestExpense": 81000000,
        "depreciationAndAmortization": 218000000,
        "ebitda": -441000000,
        "ebit": -659000000,
        "nonOperatingIncomeExcludingInterest": -2000000,
        "operatingIncome": -661000000,
        "totalOtherIncomeExpensesNet": -79000000,
        "incomeBeforeTax": -740000000,
        "incomeTaxExpense": 3000000,
        "netIncomeFromContinuingOperations": -743000000,
        "netIncomeFromDiscontinuedOperations": 0,
        "otherAdjustmentsToNetIncome": 0,
        "netIncome": -743000000,
        "netIncomeDeductions": 1000000,
        "bottomLineNetIncome": -744000000,
        "eps": -0.7032,
        "epsDiluted": -0.7032,
        "weightedAverageShsOut": 1058000000,
        "weightedAverageShsOutDil": 1058000000
    },
    {
        "date": "2023-12-31",
        "symbol": "RIVN",
        "reportedCurrency": "USD",
        "cik": "0001874178",
        "filingDate": "2024-02-26",
        "acceptedDate": "2024-02-26 17:14:54",
        "fiscalYear": "2023",
        "period": "Q4",
        "revenue": 1315000000,
        "costOfRevenue": 1921000000,
        "grossProfit": -606000000,
        "researchAndDevelopmentExpenses": 526000000,
        "generalAndAdministrativeExpenses": 429000000,
        "sellingAndMarketingExpenses": 20000000,
        "sellingGeneralAndAdministrativeExpenses": 449000000,
        "otherExpenses": 0,
        "operatingExpenses": 975000000,
        "costAndExpenses": 2896000000,
        "netInterestIncome": 58000000,
        "interestIncome": 131000000,
        "interestExpense": 73000000,
        "depreciationAndAmortization": 270000000,
        "ebitda": -1178000000,
        "ebit": -1448000000,
        "nonOperatingIncomeExcludingInterest": -133000000,
        "operatingIncome": -1581000000,
        "totalOtherIncomeExpensesNet": 60000000,
        "incomeBeforeTax": -1521000000,
        "incomeTaxExpense": 0,
        "netIncomeFromContinuingOperations": -1521000000,
        "netIncomeFromDiscontinuedOperations": 0,
        "otherAdjustmentsToNetIncome": 0,
        "netIncome": -1521000000,
        "netIncomeDeductions": 0,
        "bottomLineNetIncome": -1521000000,
        "eps": -1.5794,
        "epsDiluted": -1.5794,
        "weightedAverageShsOut": 963000000,
        "weightedAverageShsOutDil": 963000000
    },
    {
        "date": "2022-12-31",
        "symbol": "RIVN",
        "reportedCurrency": "USD",
        "cik": "0001874178",
        "filingDate": "2023-02-28",
        "acceptedDate": "2023-02-28 17:15:26",
        "fiscalYear": "2022",
        "period": "Q4",
        "revenue": 663000000,
        "costOfRevenue": 1663000000,
        "grossProfit": -1000000000,
        "researchAndDevelopmentExpenses": 402000000,
        "generalAndAdministrativeExpenses": 0,
        "sellingAndMarketingExpenses": 0,
        "sellingGeneralAndAdministrativeExpenses": 393000000,
        "otherExpenses": 0,
        "operatingExpenses": 795000000,
        "costAndExpenses": 2458000000,
        "netInterestIncome": 66000000,
        "interestIncome": 99000000,
        "interestExpense": 33000000,
        "depreciationAndAmortization": 199000000,
        "ebitda": -1491000000,
        "ebit": -1690000000,
        "nonOperatingIncomeExcludingInterest": -105000000,
        "operatingIncome": -1795000000,
        "totalOtherIncomeExpensesNet": 72000000,
        "incomeBeforeTax": -1723000000,
        "incomeTaxExpense": 0,
        "netIncomeFromContinuingOperations": -1723000000,
        "netIncomeFromDiscontinuedOperations": 0,
        "otherAdjustmentsToNetIncome": 0,
        "netIncome": -1723000000,
        "netIncomeDeductions": 0,
        "bottomLineNetIncome": -1723000000,
        "eps": -1.8667,
        "epsDiluted": -1.8667,
        "weightedAverageShsOut": 915010638,
        "weightedAverageShsOutDil": 915500000
    },
    {
        "date": "2021-12-31",
        "symbol": "RIVN",
        "reportedCurrency": "USD",
        "cik": "0001874178",
        "filingDate": "2022-03-31",
        "acceptedDate": "2022-03-31 08:22:02",
        "fiscalYear": "2021",
        "period": "Q4",
        "revenue": 54000000,
        "costOfRevenue": 437000000,
        "grossProfit": -383000000,
        "researchAndDevelopmentExpenses": 726000000,
        "generalAndAdministrativeExpenses": 0,
        "sellingAndMarketingExpenses": 0,
        "sellingGeneralAndAdministrativeExpenses": 682000000,
        "otherExpenses": 663000000,
        "operatingExpenses": 2071000000,
        "costAndExpenses": 2508000000,
        "netInterestIncome": -21000000,
        "interestIncome": 1000000,
        "interestExpense": 22000000,
        "depreciationAndAmortization": 113000000,
        "ebitda": -2326000000,
        "ebit": -2439000000,
        "nonOperatingIncomeExcludingInterest": -15000000,
        "operatingIncome": -2454000000,
        "totalOtherIncomeExpensesNet": -7000000,
        "incomeBeforeTax": -2461000000,
        "incomeTaxExpense": 0,
        "netIncomeFromContinuingOperations": -2461000000,
        "netIncomeFromDiscontinuedOperations": 0,
        "otherAdjustmentsToNetIncome": 0,
        "netIncome": -2461000000,
        "netIncomeDeductions": 0,
        "bottomLineNetIncome": -2461000000,
        "eps": -4.83,
        "epsDiluted": -4.83,
        "weightedAverageShsOut": 510000020,
        "weightedAverageShsOutDil": 510000000
    },
    {
        "date": "2020-12-31",
        "symbol": "RIVN",
        "reportedCurrency": "USD",
        "cik": "0001874178",
        "filingDate": "2020-12-31",
        "acceptedDate": "2020-12-31 00:00:00",
        "fiscalYear": "2020",
        "period": "Q4",
        "revenue": 0,
        "costOfRevenue": 12000000,
        "grossProfit": -12000000,
        "researchAndDevelopmentExpenses": 255000000,
        "generalAndAdministrativeExpenses": 0,
        "sellingAndMarketingExpenses": 0,
        "sellingGeneralAndAdministrativeExpenses": 86000000,
        "otherExpenses": 0,
        "operatingExpenses": 341000000,
        "costAndExpenses": 353000000,
        "netInterestIncome": -1000000,
        "interestIncome": 1000000,
        "interestExpense": 2000000,
        "depreciationAndAmortization": 12000000,
        "ebitda": -339000000,
        "ebit": -351000000,
        "nonOperatingIncomeExcludingInterest": -2000000,
        "operatingIncome": -353000000,
        "totalOtherIncomeExpensesNet": 0,
        "incomeBeforeTax": -353000000,
        "incomeTaxExpense": 0,
        "netIncomeFromContinuingOperations": -353000000,
        "netIncomeFromDiscontinuedOperations": 0,
        "otherAdjustmentsToNetIncome": 0,
        "netIncome": -353000000,
        "netIncomeDeductions": 0,
        "bottomLineNetIncome": -353000000,
        "eps": -3.4,
        "epsDiluted": -3.4,
        "weightedAverageShsOut": 103679871,
        "weightedAverageShsOutDil": 104000000
    }
]