[
    {
        "date": "2025-11-30",
        "symbol": "CCL",
        "reportedCurrency": "USD",
        "cik": "0000815097",
        "filingDate": "2025-12-19",
        "acceptedDate": "2025-12-19 09:17:01",
        "fiscalYear": "2025",
        "period": "Q4",
        "cashAndCashEquivalents": 1928000000,
        "shortTermInvestments": 0,
        "cashAndShortTermInvestments": 1928000000,
        "netReceivables": 678000000,
        "accountsReceivables": 678000000,
        "otherReceivables": 0,
        "inventory": 505000000,
        "prepaids": 0,
        "otherCurrentAssets": 1108000000,
        "totalCurrentAssets": 4219000000,
        "propertyPlantEquipmentNet": 44822000000,
        "goodwill": 579000000,
        "intangibleAssets": 1177000000,
        "goodwillAndIntangibleAssets": 1756000000,
        "longTermInvestments": 0,
        "taxAssets": 0,
        "otherNonCurrentAssets": 890000000,
        "totalNonCurrentAssets": 47468000000,
        "otherAssets": 0,
        "totalAssets": 51687000000,
        "totalPayables": 1245000000,
        "accountPayables": 1245000000,
        "otherPayables": 0,
        "accruedExpenses": 0,
        "shortTermDebt": 2778000000,
        "capitalLeaseObligationsCurrent": 0,
        "taxPayables": 0,
        "deferredRevenue": 0,
        "otherCurrentLiabilities": 9069000000,
        "totalCurrentLiabilities": 13092000000,
        "longTermDebt": 24037000000,
        "capitalLeaseObligationsNonCurrent": 1178000000,
        "deferredRevenueNonCurrent": 0,
        "deferredTaxLiabilitiesNonCurrent": 0,
        "otherNonCurrentLiabilities": 1097000000,
        "totalNonCurrentLiabilities": 26312000000,
        "otherLiabilities": 0,
        "capitalLeaseObligations": 1178000000,
        "totalLiabilities": 39404000000,
        "treasuryStock": -8364000000,
        "preferredStock": 0,
        "commonStock": 374000000,
        "retainedEarnings": 4817000000,
        "additionalPaidInCapital": 17267000000,
        "accumulatedOtherComprehensiveIncomeLoss": -1810000000,
        "otherTotalStockholdersEquity": 0,
        "totalStockholdersEquity": 12284000000,
        "totalEquity": 12284000000,
        "minorityInterest": 0,
        "totalLiabilitiesAndTotalEquity": 51687000000,
        "totalInvestments": 0,
        "totalDebt": 27993000000,
        "netDebt": 26065000000
    },
    {
        "date": "2024-11-30",
        "symbol": "CCL",
        "reportedCurrency": "USD",
        "cik": "0000815097",
        "filingDate": "2025-01-27",
        "acceptedDate": "2025-01-27 06:11:17",
        "fiscalYear": "2024",
        "period": "Q4",
        "cashAndCashEquivalents": 1210000000,
        "shortTermInvestments": 0,
        "cashAndShortTermInvestments": 1210000000,
        "netReceivables": 590000000,
        "accountsReceivables": 590000000,
        "otherReceivables": 0,
        "inventory": 507000000,
        "prepaids": 0,
        "otherCurrentAssets": 1071000000,
        "totalCurrentAssets": 3378000000,
        "propertyPlantEquipmentNet": 43163000000,
        "goodwill": 579000000,
        "intangibleAssets": 1163000000,
        "goodwillAndIntangibleAssets": 1742000000,
        "longTermInvestments": 184000000,
        "taxAssets": 0,
        "otherNonCurrentAssets": 591000000,
        "totalNonCurrentAssets": 45680000000,
        "otherAssets": -1000000,
        "totalAssets": 49057000000,
        "totalPayables": 1133000000,
        "accountPayables": 1133000000,
        "otherPayables": 0,
        "accruedExpenses": 2358000000,
        "shortTermDebt": 1538000000,
        "capitalLeaseObligationsCurrent": 163000000,
        "taxPayables": 0,
        "deferredRevenue": 6425000000,
        "otherCurrentLiabilities": 0,
        "totalCurrentLiabilities": 11617000000,
        "longTermDebt": 25936000000,
        "capitalLeaseObligationsNonCurrent": 1239000000,
        "deferredRevenueNonCurrent": 0,
        "deferredTaxLiabilitiesNonCurrent": 0,
        "otherNonCurrentLiabilities": 1013000000,
        "totalNonCurrentLiabilities": 28189000000,
        "otherLiabilities": 0,
        "capitalLeaseObligations": 1402000000,
        "totalLiabilities": 39806000000,
        "treasuryStock": -8404000000,
        "preferredStock": 0,
        "commonStock": 374000000,
        "retainedEarnings": 2101000000,
        "additionalPaidInCapital": 17155000000,
        "accumulatedOtherComprehensiveIncomeLoss": -1974000000,
        "otherTotalStockholdersEquity": 0,
        "totalStockholdersEquity": 9252000000,
        "totalEquity": 9252000000,
        "minorityInterest": 0,
        "totalLiabilitiesAndTotalEquity": 49057000000,
        "totalInvestments": 184000000,
        "totalDebt": 28876000000,
        "netDebt": 27666000000
    },
    {
        "date": "2023-11-30",
        "symbol": "CCL",
        "reportedCurrency": "USD",
        "cik": "0000815097",
        "filingDate": "2024-01-26",
        "acceptedDate": "2024-01-26 10:09:35",
        "fiscalYear": "2023",
        "period": "Q4",
        "cashAndCashEquivalents": 2415000000,
        "shortTermInvestments": 0,
        "cashAndShortTermInvestments": 2415000000,
        "netReceivables": 556000000,
        "accountsReceivables": 556000000,
        "otherReceivables": 0,
        "inventory": 528000000,
        "prepaids": 0,
        "otherCurrentAssets": 1767000000,
        "totalCurrentAssets": 5266000000,
        "propertyPlantEquipmentNet": 41381000000,
        "goodwill": 579000000,
        "intangibleAssets": 1169000000,
        "goodwillAndIntangibleAssets": 1748000000,
        "longTermInvestments": 149000000,
        "taxAssets": 0,
        "otherNonCurrentAssets": 576000000,
        "totalNonCurrentAssets": 43854000000,
        "otherAssets": 0,
        "totalAssets": 49120000000,
        "totalPayables": 1168000000,
        "accountPayables": 1168000000,
        "otherPayables": 0,
        "accruedExpenses": 2003000000,
        "shortTermDebt": 2089000000,
        "capitalLeaseObligationsCurrent": 149000000,
        "taxPayables": 0,
        "deferredRevenue": 6072000000,
        "otherCurrentLiabilities": 0,
        "totalCurrentLiabilities": 11481000000,
        "longTermDebt": 28483000000,
        "capitalLeaseObligationsNonCurrent": 1170000000,
        "deferredRevenueNonCurrent": 0,
        "deferredTaxLiabilitiesNonCurrent": 0,
        "otherNonCurrentLiabilities": 1104000000,
        "totalNonCurrentLiabilities": 30757000000,
        "otherLiabilities": 0,
        "capitalLeaseObligations": 1319000000,
        "totalLiabilities": 42238000000,
        "treasuryStock": -8449000000,
        "preferredStock": 0,
        "commonStock": 373000000,
        "retainedEarnings": 185000000,
        "additionalPaidInCapital": 16712000000,
        "accumulatedOtherComprehensiveIncomeLoss": -1939000000,
        "otherTotalStockholdersEquity": 0,
        "totalStockholdersEquity": 6882000000,
        "totalEquity": 6882000000,
        "minorityInterest": 0,
        "totalLiabilitiesAndTotalEquity": 49120000000,
        "totalInvestments": 149000000,
        "totalDebt": 31891000000,
        "netDebt": 29476000000
    },
    {
        "date": "2022-11-30",
        "symbol": "CCL",
        "reportedCurrency": "USD",
        "cik": "0000815097",
        "filingDate": "2023-01-27",
        "acceptedDate": "2023-01-27 11:36:20",
        "fiscalYear": "2022",
        "period": "Q4",
        "cashAndCashEquivalents": 4029000000,
        "shortTermInvestments": 0,
        "cashAndShortTermInvestments": 4029000000,
        "netReceivables": 395000000,
        "accountsReceivables": 395000000,
        "otherReceivables": 0,
        "inventory": 428000000,
        "prepaids": 652000000,
        "otherCurrentAssets": 1988000000,
        "totalCurrentAssets": 7492000000,
        "propertyPlantEquipmentNet": 39961000000,
        "goodwill": 579000000,
        "intangibleAssets": 1156000000,
        "goodwillAndIntangibleAssets": 1735000000,
        "longTermInvestments": 1000000,
        "taxAssets": 0,
        "otherNonCurrentAssets": 2514000000,
        "totalNonCurrentAssets": 44211000000,
        "otherAssets": 0,
        "totalAssets": 51703000000,
        "totalPayables": 1050000000,
        "accountPayables": 1050000000,
        "otherPayables": 0,
        "accruedExpenses": 1942000000,
        "shortTermDebt": 2593000000,
        "capitalLeaseObligationsCurrent": 146000000,
        "taxPayables": 0,
        "deferredRevenue": 4874000000,
        "otherCurrentLiabilities": 0,
        "totalCurrentLiabilities": 10605000000,
        "longTermDebt": 31953000000,
        "capitalLeaseObligationsNonCurrent": 1189000000,
        "deferredRevenueNonCurrent": 0,
        "deferredTaxLiabilitiesNonCurrent": 0,
        "otherNonCurrentLiabilities": 892000000,
        "totalNonCurrentLiabilities": 34034000000,
        "otherLiabilities": 0,
        "capitalLeaseObligations": 1335000000,
        "totalLiabilities": 44639000000,
        "treasuryStock": -8468000000,
        "preferredStock": 0,
        "commonStock": 373000000,
        "retainedEarnings": 269000000,
        "additionalPaidInCapital": 16872000000,
        "accumulatedOtherComprehensiveIncomeLoss": -1982000000,
        "otherTotalStockholdersEquity": 0,
        "totalStockholdersEquity": 7064000000,
        "totalEquity": 7064000000,
        "minorityInterest": 0,
        "totalLiabilitiesAndTotalEquity": 51703000000,
        "totalInvestments": 1000000,
        "totalDebt": 35881000000,
        "netDebt": 31852000000
    },
    {
        "date": "2021-11-30",
        "symbol": "CCL",
        "reportedCurrency": "USD",
        "cik": "0000815097",
        "filingDate": "2022-01-27",
        "acceptedDate": "2022-01-27 12:40:15",
        "fiscalYear": "2021",
        "period": "Q4",
        "cashAndCashEquivalents": 8939000000,
        "shortTermInvestments": 200000000,
        "cashAndShortTermInvestments": 9139000000,
        "netReceivables": 246000000,
        "accountsReceivables": 246000000,
        "otherReceivables": 0,
        "inventory": 356000000,
        "prepaids": 379000000,
        "otherCurrentAssets": 13000000,
        "totalCurrentAssets": 10133000000,
        "propertyPlantEquipmentNet": 39440000000,
        "goodwill": 579000000,
        "intangibleAssets": 1181000000,
        "goodwillAndIntangibleAssets": 1760000000,
        "longTermInvestments": 0,
        "taxAssets": 0,
        "otherNonCurrentAssets": 2011000000,
        "totalNonCurrentAssets": 43211000000,
        "otherAssets": 0,
        "totalAssets": 53344000000,
        "totalPayables": 797000000,
        "accountPayables": 797000000,
        "otherPayables": 0,
        "accruedExpenses": 1641000000,
        "shortTermDebt": 4717000000,
        "capitalLeaseObligationsCurrent": 142000000,
        "taxPayables": 0,
        "deferredRevenue": 3112000000,
        "otherCurrentLiabilities": -1000000,
        "totalCurrentLiabilities": 10408000000,
        "longTermDebt": 28509000000,
        "capitalLeaseObligationsNonCurrent": 1239000000,
        "deferredRevenueNonCurrent": 0,
        "deferredTaxLiabilitiesNonCurrent": 0,
        "otherNonCurrentLiabilities": 1044000000,
        "totalNonCurrentLiabilities": 30791000000,
        "otherLiabilities": 0,
        "capitalLeaseObligations": 1381000000,
        "totalLiabilities": 41199000000,
        "treasuryStock": -8466000000,
        "preferredStock": 0,
        "commonStock": 372000000,
        "retainedEarnings": 6448000000,
        "additionalPaidInCapital": 15292000000,
        "accumulatedOtherComprehensiveIncomeLoss": -1501000000,
        "otherTotalStockholdersEquity": 0,
        "totalStockholdersEquity": 12145000000,
        "totalEquity": 12145000000,
        "minorityInterest": 0,
        "totalLiabilitiesAndTotalEquity": 53344000000,
        "totalInvestments": 200000000,
        "totalDebt": 34607000000,
        "netDebt": 25668000000
    }
]