[
    {
        "date": "2025-09-30",
        "symbol": "UAL",
        "reportedCurrency": "USD",
        "cik": "0000100517",
        "filingDate": "2025-10-16",
        "acceptedDate": "2025-10-16 16:21:05",
        "fiscalYear": "2025",
        "period": "Q3",
        "cashAndCashEquivalents": 6730000000,
        "shortTermInvestments": 6599000000,
        "cashAndShortTermInvestments": 13329000000,
        "netReceivables": 2433000000,
        "accountsReceivables": 2433000000,
        "otherReceivables": 0,
        "inventory": 1588000000,
        "prepaids": 0,
        "otherCurrentAssets": 744000000,
        "totalCurrentAssets": 18094000000,
        "propertyPlantEquipmentNet": 49789000000,
        "goodwill": 4527000000,
        "intangibleAssets": 2662000000,
        "goodwillAndIntangibleAssets": 7189000000,
        "longTermInvestments": 1242000000,
        "taxAssets": 0,
        "otherNonCurrentAssets": -1000000,
        "totalNonCurrentAssets": 58219000000,
        "otherAssets": 0,
        "totalAssets": 76313000000,
        "totalPayables": 4636000000,
        "accountPayables": 4636000000,
        "otherPayables": 0,
        "accruedExpenses": 3555000000,
        "shortTermDebt": 5184000000,
        "capitalLeaseObligationsCurrent": 0,
        "taxPayables": 0,
        "deferredRevenue": 12980000000,
        "otherCurrentLiabilities": 764000000,
        "totalCurrentLiabilities": 27119000000,
        "longTermDebt": 20807000000,
        "capitalLeaseObligationsNonCurrent": 5331000000,
        "deferredRevenueNonCurrent": 4060000000,
        "deferredTaxLiabilitiesNonCurrent": 2206000000,
        "otherNonCurrentLiabilities": 2482000000,
        "totalNonCurrentLiabilities": 34886000000,
        "otherLiabilities": 0,
        "capitalLeaseObligations": 5331000000,
        "totalLiabilities": 62004000000,
        "treasuryStock": 0,
        "preferredStock": 0,
        "commonStock": 4000000,
        "retainedEarnings": 9049000000,
        "additionalPaidInCapital": 0,
        "accumulatedOtherComprehensiveIncomeLoss": 123000000,
        "otherTotalStockholdersEquity": 5133000000,
        "totalStockholdersEquity": 14309000000,
        "totalEquity": 14309000000,
        "minorityInterest": 0,
        "totalLiabilitiesAndTotalEquity": 76313000000,
        "totalInvestments": 7841000000,
        "totalDebt": 31322000000,
        "netDebt": 24592000000
    },
    {
        "date": "2024-09-30",
        "symbol": "UAL",
        "reportedCurrency": "USD",
        "cik": "0000100517",
        "filingDate": "2024-10-16",
        "acceptedDate": "2024-10-16 16:09:22",
        "fiscalYear": "2024",
        "period": "Q3",
        "cashAndCashEquivalents": 8812000000,
        "shortTermInvestments": 5352000000,
        "cashAndShortTermInvestments": 14164000000,
        "netReceivables": 2042000000,
        "accountsReceivables": 2042000000,
        "otherReceivables": 0,
        "inventory": 1639000000,
        "prepaids": 0,
        "otherCurrentAssets": 726000000,
        "totalCurrentAssets": 18571000000,
        "propertyPlantEquipmentNet": 45462000000,
        "goodwill": 4527000000,
        "intangibleAssets": 2691000000,
        "goodwillAndIntangibleAssets": 7218000000,
        "longTermInvestments": 1209000000,
        "taxAssets": 0,
        "otherNonCurrentAssets": 180000000,
        "totalNonCurrentAssets": 54069000000,
        "otherAssets": 0,
        "totalAssets": 72640000000,
        "totalPayables": 4008000000,
        "accountPayables": 4008000000,
        "otherPayables": 0,
        "accruedExpenses": 2802000000,
        "shortTermDebt": 3279000000,
        "capitalLeaseObligationsCurrent": 647000000,
        "taxPayables": 0,
        "deferredRevenue": 11791000000,
        "otherCurrentLiabilities": 838000000,
        "totalCurrentLiabilities": 23365000000,
        "longTermDebt": 22207000000,
        "capitalLeaseObligationsNonCurrent": 4521000000,
        "deferredRevenueNonCurrent": 4057000000,
        "deferredTaxLiabilitiesNonCurrent": 1224000000,
        "otherNonCurrentLiabilities": 5829000000,
        "totalNonCurrentLiabilities": 37838000000,
        "otherLiabilities": 0,
        "capitalLeaseObligations": 5168000000,
        "totalLiabilities": 61203000000,
        "treasuryStock": -3299000000,
        "preferredStock": 0,
        "commonStock": 4000000,
        "retainedEarnings": 5896000000,
        "additionalPaidInCapital": 8945000000,
        "accumulatedOtherComprehensiveIncomeLoss": -109000000,
        "otherTotalStockholdersEquity": 0,
        "totalStockholdersEquity": 11437000000,
        "totalEquity": 11437000000,
        "minorityInterest": 0,
        "totalLiabilitiesAndTotalEquity": 72640000000,
        "totalInvestments": 6561000000,
        "totalDebt": 30585000000,
        "netDebt": 21773000000
    },
    {
        "date": "2023-09-30",
        "symbol": "UAL",
        "reportedCurrency": "USD",
        "cik": "0000100517",
        "filingDate": "2023-10-18",
        "acceptedDate": "2023-10-18 16:07:57",
        "fiscalYear": "2023",
        "period": "Q3",
        "cashAndCashEquivalents": 7478000000,
        "shortTermInvestments": 9608000000,
        "cashAndShortTermInvestments": 17086000000,
        "netReceivables": 2193000000,
        "accountsReceivables": 2193000000,
        "otherReceivables": 0,
        "inventory": 1513000000,
        "prepaids": 728000000,
        "otherCurrentAssets": 392000000,
        "totalCurrentAssets": 21912000000,
        "propertyPlantEquipmentNet": 42335000000,
        "goodwill": 4527000000,
        "intangibleAssets": 2735000000,
        "goodwillAndIntangibleAssets": 7262000000,
        "longTermInvestments": 1404000000,
        "taxAssets": 0,
        "otherNonCurrentAssets": 240000000,
        "totalNonCurrentAssets": 51241000000,
        "otherAssets": 0,
        "totalAssets": 73153000000,
        "totalPayables": 4206000000,
        "accountPayables": 4206000000,
        "otherPayables": 0,
        "accruedExpenses": 3815000000,
        "shortTermDebt": 3649000000,
        "capitalLeaseObligationsCurrent": 869000000,
        "taxPayables": 0,
        "deferredRevenue": 11361000000,
        "otherCurrentLiabilities": 856000000,
        "totalCurrentLiabilities": 24756000000,
        "longTermDebt": 25932000000,
        "capitalLeaseObligationsNonCurrent": 4564000000,
        "deferredRevenueNonCurrent": 4107000000,
        "deferredTaxLiabilitiesNonCurrent": 472000000,
        "otherNonCurrentLiabilities": 4469000000,
        "totalNonCurrentLiabilities": 39544000000,
        "otherLiabilities": 0,
        "capitalLeaseObligations": 5433000000,
        "totalLiabilities": 64300000000,
        "treasuryStock": -3442000000,
        "preferredStock": 0,
        "commonStock": 4000000,
        "retainedEarnings": 3232000000,
        "additionalPaidInCapital": 8968000000,
        "accumulatedOtherComprehensiveIncomeLoss": 91000000,
        "otherTotalStockholdersEquity": 0,
        "totalStockholdersEquity": 8853000000,
        "totalEquity": 8853000000,
        "minorityInterest": 0,
        "totalLiabilitiesAndTotalEquity": 73153000000,
        "totalInvestments": 11012000000,
        "totalDebt": 35014000000,
        "netDebt": 27536000000
    },
    {
        "date": "2022-09-30",
        "symbol": "UAL",
        "reportedCurrency": "USD",
        "cik": "0000100517",
        "filingDate": "2022-10-19",
        "acceptedDate": "2022-10-19 16:08:15",
        "fiscalYear": "2022",
        "period": "Q3",
        "cashAndCashEquivalents": 11258000000,
        "shortTermInvestments": 7437000000,
        "cashAndShortTermInvestments": 18695000000,
        "netReceivables": 2034000000,
        "accountsReceivables": 2034000000,
        "otherReceivables": 0,
        "inventory": 1116000000,
        "prepaids": 783000000,
        "otherCurrentAssets": 61000000,
        "totalCurrentAssets": 22689000000,
        "propertyPlantEquipmentNet": 36786000000,
        "goodwill": 4527000000,
        "intangibleAssets": 2772000000,
        "goodwillAndIntangibleAssets": 7299000000,
        "longTermInvestments": 1285000000,
        "taxAssets": 701000000,
        "otherNonCurrentAssets": 208000000,
        "totalNonCurrentAssets": 46279000000,
        "otherAssets": 0,
        "totalAssets": 68968000000,
        "totalPayables": 3534000000,
        "accountPayables": 3534000000,
        "otherPayables": 0,
        "accruedExpenses": 1841000000,
        "shortTermDebt": 2955000000,
        "capitalLeaseObligationsCurrent": 618000000,
        "taxPayables": 0,
        "deferredRevenue": 11389000000,
        "otherCurrentLiabilities": 1652000000,
        "totalCurrentLiabilities": 21989000000,
        "longTermDebt": 28490000000,
        "capitalLeaseObligationsNonCurrent": 4915000000,
        "deferredRevenueNonCurrent": 3936000000,
        "deferredTaxLiabilitiesNonCurrent": 0,
        "otherNonCurrentLiabilities": 4740000000,
        "totalNonCurrentLiabilities": 42081000000,
        "otherLiabilities": 0,
        "capitalLeaseObligations": 5533000000,
        "totalLiabilities": 64070000000,
        "treasuryStock": -3533000000,
        "preferredStock": 0,
        "commonStock": 4000000,
        "retainedEarnings": 421000000,
        "additionalPaidInCapital": 8970000000,
        "accumulatedOtherComprehensiveIncomeLoss": -964000000,
        "otherTotalStockholdersEquity": 0,
        "totalStockholdersEquity": 4898000000,
        "totalEquity": 4898000000,
        "minorityInterest": 0,
        "totalLiabilitiesAndTotalEquity": 68968000000,
        "totalInvestments": 8722000000,
        "totalDebt": 36978000000,
        "netDebt": 25720000000
    },
    {
        "date": "2021-09-30",
        "symbol": "UAL",
        "reportedCurrency": "USD",
        "cik": "0000100517",
        "filingDate": "2021-10-20",
        "acceptedDate": "2021-10-20 16:17:20",
        "fiscalYear": "2021",
        "period": "Q3",
        "cashAndCashEquivalents": 19256000000,
        "shortTermInvestments": 166000000,
        "cashAndShortTermInvestments": 19422000000,
        "netReceivables": 1709000000,
        "accountsReceivables": 1709000000,
        "otherReceivables": 0,
        "inventory": 955000000,
        "prepaids": 717000000,
        "otherCurrentAssets": 254000000,
        "totalCurrentAssets": 23057000000,
        "propertyPlantEquipmentNet": 36825000000,
        "goodwill": 4527000000,
        "intangibleAssets": 2815000000,
        "goodwillAndIntangibleAssets": 7342000000,
        "longTermInvestments": 1336000000,
        "taxAssets": 519000000,
        "otherNonCurrentAssets": 215000000,
        "totalNonCurrentAssets": 46237000000,
        "otherAssets": 0,
        "totalAssets": 69294000000,
        "totalPayables": 2199000000,
        "accountPayables": 2199000000,
        "otherPayables": 0,
        "accruedExpenses": 2207000000,
        "shortTermDebt": 2269000000,
        "capitalLeaseObligationsCurrent": 685000000,
        "taxPayables": 0,
        "deferredRevenue": 8492000000,
        "otherCurrentLiabilities": 1083000000,
        "totalCurrentLiabilities": 16935000000,
        "longTermDebt": 31520000000,
        "capitalLeaseObligationsNonCurrent": 5413000000,
        "deferredRevenueNonCurrent": 4088000000,
        "deferredTaxLiabilitiesNonCurrent": 0,
        "otherNonCurrentLiabilities": 5907000000,
        "totalNonCurrentLiabilities": 46928000000,
        "otherLiabilities": 0,
        "capitalLeaseObligations": 6098000000,
        "totalLiabilities": 63863000000,
        "treasuryStock": -3814000000,
        "preferredStock": 0,
        "commonStock": 4000000,
        "retainedEarnings": 1271000000,
        "additionalPaidInCapital": 9094000000,
        "accumulatedOtherComprehensiveIncomeLoss": -1124000000,
        "otherTotalStockholdersEquity": 0,
        "totalStockholdersEquity": 5431000000,
        "totalEquity": 5431000000,
        "minorityInterest": 0,
        "totalLiabilitiesAndTotalEquity": 69294000000,
        "totalInvestments": 1502000000,
        "totalDebt": 39887000000,
        "netDebt": 20631000000
    }
]