[
    {
        "date": "2025-05-31",
        "symbol": "TLRY",
        "reportedCurrency": "USD",
        "cik": "0001731348",
        "filingDate": "2025-07-29",
        "acceptedDate": "2025-07-28 19:22:54",
        "fiscalYear": "2025",
        "period": "Q4",
        "revenue": 308104681,
        "costOfRevenue": 215299355,
        "grossProfit": 92805326,
        "researchAndDevelopmentExpenses": 46654,
        "generalAndAdministrativeExpenses": 49820102,
        "sellingAndMarketingExpenses": 31904789,
        "sellingGeneralAndAdministrativeExpenses": 81724892,
        "otherExpenses": 1992456929,
        "operatingExpenses": 2074228475,
        "costAndExpenses": 2289527830,
        "netInterestIncome": -5442105,
        "interestIncome": 0,
        "interestExpense": 5442105,
        "depreciationAndAmortization": 46764235,
        "ebitda": -1843690950,
        "ebit": -1890455185,
        "nonOperatingIncomeExcludingInterest": -90967963,
        "operatingIncome": -1981423149,
        "totalOtherIncomeExpensesNet": 69911708,
        "incomeBeforeTax": -1911511441,
        "incomeTaxExpense": -171718600,
        "netIncomeFromContinuingOperations": -1739792840,
        "netIncomeFromDiscontinuedOperations": 0,
        "otherAdjustmentsToNetIncome": 0,
        "netIncome": -1746516571,
        "netIncomeDeductions": 0,
        "bottomLineNetIncome": -1746516571,
        "eps": -17.8,
        "epsDiluted": -17.8,
        "weightedAverageShsOut": 97796000,
        "weightedAverageShsOutDil": 97796000
    },
    {
        "date": "2024-05-31",
        "symbol": "TLRY",
        "reportedCurrency": "USD",
        "cik": "0001731348",
        "filingDate": "2024-07-30",
        "acceptedDate": "2024-07-29 18:59:52",
        "fiscalYear": "2024",
        "period": "Q4",
        "revenue": 313230316,
        "costOfRevenue": 201022677,
        "grossProfit": 112207639,
        "researchAndDevelopmentExpenses": 536852,
        "generalAndAdministrativeExpenses": 65117220,
        "sellingAndMarketingExpenses": 35147493,
        "sellingGeneralAndAdministrativeExpenses": 100264713,
        "otherExpenses": 33923905,
        "operatingExpenses": 134725471,
        "costAndExpenses": 335748148,
        "netInterestIncome": -12884461,
        "interestIncome": 0,
        "interestExpense": 12884461,
        "depreciationAndAmortization": 43234346,
        "ebitda": 15005983,
        "ebit": -28228362,
        "nonOperatingIncomeExcludingInterest": 5710530,
        "operatingIncome": -22517831,
        "totalOtherIncomeExpensesNet": -36078128,
        "incomeBeforeTax": -58595960,
        "incomeTaxExpense": -37646446,
        "netIncomeFromContinuingOperations": -20949513,
        "netIncomeFromDiscontinuedOperations": 0,
        "otherAdjustmentsToNetIncome": 0,
        "netIncome": -43257509,
        "netIncomeDeductions": 0,
        "bottomLineNetIncome": -43257509,
        "eps": -0.545028,
        "epsDiluted": -0.545028,
        "weightedAverageShsOut": 79367500,
        "weightedAverageShsOutDil": 79367500
    },
    {
        "date": "2023-05-31",
        "symbol": "TLRY",
        "reportedCurrency": "USD",
        "cik": "0001731348",
        "filingDate": "2023-07-26",
        "acceptedDate": "2023-07-26 17:01:16",
        "fiscalYear": "2023",
        "period": "Q4",
        "revenue": 248096324,
        "costOfRevenue": 157629554,
        "grossProfit": 90466769,
        "researchAndDevelopmentExpenses": 242455.2,
        "generalAndAdministrativeExpenses": 64412264,
        "sellingAndMarketingExpenses": 22693806,
        "sellingGeneralAndAdministrativeExpenses": 87106071,
        "otherExpenses": 124318903,
        "operatingExpenses": 211667430,
        "costAndExpenses": 369296984,
        "netInterestIncome": -6771234,
        "interestIncome": 0,
        "interestExpense": 6771234,
        "depreciationAndAmortization": 39052797,
        "ebitda": -60131583,
        "ebit": -99184381,
        "nonOperatingIncomeExcludingInterest": -22016279,
        "operatingIncome": -121200660,
        "totalOtherIncomeExpensesNet": -29238750,
        "incomeBeforeTax": -150439410,
        "incomeTaxExpense": 10953587,
        "netIncomeFromContinuingOperations": -161392997,
        "netIncomeFromDiscontinuedOperations": 0,
        "otherAdjustmentsToNetIncome": 0,
        "netIncome": -186842711,
        "netIncomeDeductions": 0,
        "bottomLineNetIncome": -186842711,
        "eps": -2.0205,
        "epsDiluted": -2.0205,
        "weightedAverageShsOut": 79879333,
        "weightedAverageShsOutDil": 79879333
    },
    {
        "date": "2022-05-31",
        "symbol": "TLRY",
        "reportedCurrency": "USD",
        "cik": "0001731348",
        "filingDate": "2022-07-28",
        "acceptedDate": "2022-07-28 16:26:46",
        "fiscalYear": "2022",
        "period": "Q4",
        "revenue": 193278939,
        "costOfRevenue": 201766447,
        "grossProfit": -8487507,
        "researchAndDevelopmentExpenses": 68071.5,
        "generalAndAdministrativeExpenses": 73074755,
        "sellingAndMarketingExpenses": 25733548,
        "sellingGeneralAndAdministrativeExpenses": 98808303,
        "otherExpenses": 481861760,
        "operatingExpenses": 580738135,
        "costAndExpenses": 782504582,
        "netInterestIncome": -6960941,
        "interestIncome": 14794205,
        "interestExpense": 21755147,
        "depreciationAndAmortization": 51391461,
        "ebitda": -508742439,
        "ebit": -560133901,
        "nonOperatingIncomeExcludingInterest": -29091742,
        "operatingIncome": -589225643,
        "totalOtherIncomeExpensesNet": 7336595,
        "incomeBeforeTax": -581889048,
        "incomeTaxExpense": -4793998,
        "netIncomeFromContinuingOperations": -577095049,
        "netIncomeFromDiscontinuedOperations": 0,
        "otherAdjustmentsToNetIncome": 0,
        "netIncome": -602736575,
        "netIncomeDeductions": 0,
        "bottomLineNetIncome": -602736575,
        "eps": -11.3,
        "epsDiluted": -11.3,
        "weightedAverageShsOut": 50866667,
        "weightedAverageShsOutDil": 50866667
    },
    {
        "date": "2021-05-31",
        "symbol": "TLRY",
        "reportedCurrency": "USD",
        "cik": "0001731348",
        "filingDate": "2021-07-28",
        "acceptedDate": "2021-07-28 16:32:48",
        "fiscalYear": "2021",
        "period": "Q4",
        "revenue": 183809457,
        "costOfRevenue": 173855295,
        "grossProfit": 9954161,
        "researchAndDevelopmentExpenses": 447000,
        "generalAndAdministrativeExpenses": 5503224,
        "sellingAndMarketingExpenses": 17448033,
        "sellingGeneralAndAdministrativeExpenses": 22951259,
        "otherExpenses": 60139901,
        "operatingExpenses": 83538163,
        "costAndExpenses": 257393459,
        "netInterestIncome": -11702820,
        "interestIncome": 2339587,
        "interestExpense": 14042408,
        "depreciationAndAmortization": 29963873,
        "ebitda": 99091018,
        "ebit": 69127143,
        "nonOperatingIncomeExcludingInterest": -142711145,
        "operatingIncome": -73584000,
        "totalOtherIncomeExpensesNet": 128668736,
        "incomeBeforeTax": 55084735,
        "incomeTaxExpense": -390871,
        "netIncomeFromContinuingOperations": 55475607,
        "netIncomeFromDiscontinuedOperations": 0,
        "otherAdjustmentsToNetIncome": -37931385,
        "netIncome": 17544221,
        "netIncomeDeductions": 0,
        "bottomLineNetIncome": 17544221,
        "eps": 2.1739,
        "epsDiluted": 2.1739,
        "weightedAverageShsOut": 44644064,
        "weightedAverageShsOutDil": 44644064
    }
]